{"mapId":11,"matchCreation":1433978472663,"matchDuration":2196,"matchId":"542495700","matchMode":"CLASSIC","matchType":"MATCHED_GAME","matchVersion":"5.11.0.270","participants":[{"championId":"105","highestAchievedSeasonTier":"BRONZE","participantId":"1","spell1Id":"4","spell2Id":"12","stats":{"winner":false},"teamId":"100"},{"championId":"245","highestAchievedSeasonTier":"UNRANKED","participantId":"2","spell1Id":"14","spell2Id":"4","stats":{"winner":false},"teamId":"100"},{"championId":"16","highestAchievedSeasonTier":"UNRANKED","participantId":"3","spell1Id":"4","spell2Id":"7","stats":{"winner":false},"teamId":"100"},{"championId":"120","highestAchievedSeasonTier":"SILVER","participantId":"4","spell1Id":"11","spell2Id":"6","stats":{"winner":false},"teamId":"100"},{"championId":"67","highestAchievedSeasonTier":"GOLD","participantId":"5","spell1Id":"4","spell2Id":"7","stats":{"winner":false},"teamId":"100"},{"championId":"245","highestAchievedSeasonTier":"GOLD","participantId":"6","spell1Id":"4","spell2Id":"14","stats":{"winner":true},"teamId":"200"},{"championId":"22","highestAchievedSeasonTier":"BRONZE","participantId":"7","spell1Id":"4","spell2Id":"21","stats":{"winner":true},"teamId":"200"},{"championId":"157","highestAchievedSeasonTier":"SILVER","participantId":"8","spell1Id":"4","spell2Id":"14","stats":{"winner":true},"teamId":"200"},{"championId":"53","highestAchievedSeasonTier":"UNRANKED","participantId":"9","spell1Id":"4","spell2Id":"3","stats":{"winner":true},"teamId":"200"},{"championId":"120","highestAchievedSeasonTier":"UNRANKED","participantId":"10","spell1Id":"4","spell2Id":"11","stats":{"winner":true},"teamId":"200"}],"platformId":"BR1","queueType":"NORMAL_5x5_BLIND","region":"BR","season":"SEASON2015","teams":[{"teamId":100},{"teamId":200}]}